tokenizer_hub/__init__.py
tokenizer_hub/__version__.py
tokenizer_hub/add_words.py
tokenizer_hub/base_tokenizer.py
tokenizer_hub/chinese_char_tokenizer.py
tokenizer_hub/custom_jieba_tokenizer.py
tokenizer_hub/nltk_custom_jieba_tokenizer.py
tokenizer_hub/nltk_tokenizer.py
tokenizer_hub/parallel_jieba_tokenizer.py
tokenizer_hub/pure_char_tokenizer.py
tokenizer_hub/purewords_tokenizer.py
tokenizer_hub/tests/__init__.py
tokenizer_hub/tests/test_chinese_char_tokenizer.py
tokenizer_hub/tests/test_custom_jieba_tokenizer.py
tokenizer_hub/tests/test_nltk_custom_jieba_tokenizer.py
tokenizer_hub/tests/test_nltk_tokenizer.py
tokenizer_hub/tests/test_pure_char_tokenizer.py
tokenizer_hub/tests/test_purewords_tokenizer.py
tokenizer_hub-0.0.1.dist-info/METADATA
tokenizer_hub-0.0.1.dist-info/RECORD
tokenizer_hub-0.0.1.dist-info/WHEEL
tokenizer_hub-0.0.1.dist-info/top_level.txt
