Metadata-Version: 2.1
Name: tokenizer-hub
Version: 0.0.1
Summary: Yoctol Natural Language Tokenizer
Home-page: https://github.com/Yoctol/tokenizer-hub
Author: Solumilken
License: MIT
Platform: UNKNOWN
Classifier: Programming Language :: Python
Classifier: Programming Language :: Python :: 3.5
Classifier: Programming Language :: Python :: 3.6
Requires-Python: >=3.5
Requires-Dist: jieba (==0.39)
Requires-Dist: nltk (==3.3.0)
Requires-Dist: purewords (==0.1.1)
